<?xml version="1.0" encoding="utf-8"?>
<!--Warning: this XML is automatically generated from the XLS. Do not modify!-->
<Datatable xmlns:xsi="http://www.w3.org/2001/XMLSchema-instance" xmlns:xsd="http://www.w3.org/2001/XMLSchema">
  <GuiElement Name="Hero_H0001">
    <Title>%Hero_H0001_Title</Title>
    <Description>%Hero_H0001_Biography</Description>
    <Icons>
      <Icon Size="Small" Path="GUI/DynamicBitmaps/Heroes/Hero_H0001"/>
      <Icon Size="Large" Path="GUI/DynamicBitmaps/Heroes/Hero_H0001_Large"/>
    </Icons>
  </GuiElement>
  <GuiElement Name="Hero_H0002">
    <Title>%Hero_H0002_Title</Title>
    <Description>%Hero_H0002_Biography</Description>
    <Icons>
      <Icon Size="Small" Path="GUI/DynamicBitmaps/Heroes/Hero_H0002"/>
      <Icon Size="Large" Path="GUI/DynamicBitmaps/Heroes/Hero_H0002_Large"/>
    </Icons>
  </GuiElement>
  <GuiElement Name="Hero_H0003">
    <Title>%Hero_H0003_Title</Title>
    <Description>%Hero_H0003_Biography</Description>
    <Icons>
      <Icon Size="Small" Path="GUI/DynamicBitmaps/Heroes/Hero_H0003"/>
      <Icon Size="Large" Path="GUI/DynamicBitmaps/Heroes/Hero_H0003_Large"/>
    </Icons>
  </GuiElement>
  <GuiElement Name="Hero_H0007">
    <Title>%Hero_H0007_Title</Title>
    <Description>%Hero_H0007_Biography</Description>
    <Icons>
      <Icon Size="Small" Path="GUI/DynamicBitmaps/Heroes/Hero_H0007"/>
      <Icon Size="Large" Path="GUI/DynamicBitmaps/Heroes/Hero_H0007_Large"/>
    </Icons>
  </GuiElement>
  <GuiElement Name="Hero_H0004">
    <Title>%Hero_H0004_Title</Title>
    <Description>%Hero_H0004_Biography</Description>
    <Icons>
      <Icon Size="Small" Path="GUI/DynamicBitmaps/Heroes/Hero_H0004"/>
      <Icon Size="Large" Path="GUI/DynamicBitmaps/Heroes/Hero_H0004_Large"/>
    </Icons>
  </GuiElement>
  <GuiElement Name="Hero_H0006">
    <Title>%Hero_H0006_Title</Title>
    <Description>%Hero_H0006_Biography</Description>
    <Icons>
      <Icon Size="Small" Path="GUI/DynamicBitmaps/Heroes/Hero_H0006"/>
      <Icon Size="Large" Path="GUI/DynamicBitmaps/Heroes/Hero_H0006_Large"/>
    </Icons>
  </GuiElement>
  <GuiElement Name="Hero_H0005">
    <Title>%Hero_H0005_Title</Title>
    <Description>%Hero_H0005_Biography</Description>
    <Icons>
      <Icon Size="Small" Path="GUI/DynamicBitmaps/Heroes/Hero_H0005"/>
      <Icon Size="Large" Path="GUI/DynamicBitmaps/Heroes/Hero_H0005_Large"/>
    </Icons>
  </GuiElement>
  <GuiElement Name="Hero_H0012">
    <Title>%Hero_H0012_Title</Title>
    <Description>%Hero_H0012_Biography</Description>
    <Icons>
      <Icon Size="Small" Path="GUI/DynamicBitmaps/Heroes/Hero_H0012"/>
      <Icon Size="Large" Path="GUI/DynamicBitmaps/Heroes/Hero_H0012_Large"/>
    </Icons>
  </GuiElement>
  <GuiElement Name="Hero_H0008">
    <Title>%Hero_H0008_Title</Title>
    <Description>%Hero_H0008_Biography</Description>
    <Icons>
      <Icon Size="Small" Path="GUI/DynamicBitmaps/Heroes/Hero_H0008"/>
      <Icon Size="Large" Path="GUI/DynamicBitmaps/Heroes/Hero_H0008_Large"/>
    </Icons>
  </GuiElement>
  <GuiElement Name="Hero_H0009">
    <Title>%Hero_H0009_Title</Title>
    <Description>%Hero_H0009_Biography</Description>
    <Icons>
      <Icon Size="Small" Path="GUI/DynamicBitmaps/Heroes/Hero_H0009"/>
      <Icon Size="Large" Path="GUI/DynamicBitmaps/Heroes/Hero_H0009_Large"/>
    </Icons>
  </GuiElement>
  <GuiElement Name="Hero_H0010">
    <Title>%Hero_H0010_Title</Title>
    <Description>%Hero_H0010_Biography</Description>
    <Icons>
      <Icon Size="Small" Path="GUI/DynamicBitmaps/Heroes/Hero_H0010"/>
      <Icon Size="Large" Path="GUI/DynamicBitmaps/Heroes/Hero_H0010_Large"/>
    </Icons>
  </GuiElement>
  <GuiElement Name="Hero_H0013">
    <Title>%Hero_H0013_Title</Title>
    <Description>%Hero_H0013_Biography</Description>
    <Icons>
      <Icon Size="Small" Path="GUI/DynamicBitmaps/Heroes/Hero_H0013"/>
      <Icon Size="Large" Path="GUI/DynamicBitmaps/Heroes/Hero_H0013_Large"/>
    </Icons>
  </GuiElement>
  <GuiElement Name="Hero_H0014">
    <Title>%Hero_H0014_Title</Title>
    <Description>%Hero_H0014_Biography</Description>
    <Icons>
      <Icon Size="Small" Path="GUI/DynamicBitmaps/Heroes/Hero_H0014"/>
      <Icon Size="Large" Path="GUI/DynamicBitmaps/Heroes/Hero_H0014_Large"/>
    </Icons>
  </GuiElement>
  <GuiElement Name="Hero_H0015">
    <Title>%Hero_H0015_Title</Title>
    <Description>%Hero_H0015_Biography</Description>
    <Icons>
      <Icon Size="Small" Path="GUI/DynamicBitmaps/Heroes/Hero_H0015"/>
      <Icon Size="Large" Path="GUI/DynamicBitmaps/Heroes/Hero_H0015_Large"/>
    </Icons>
  </GuiElement>
  <GuiElement Name="Hero_H0016">
    <Title>%Hero_H0016_Title</Title>
    <Description>%Hero_H0016_Biography</Description>
    <Icons>
      <Icon Size="Small" Path="GUI/DynamicBitmaps/Heroes/Hero_H0016"/>
      <Icon Size="Large" Path="GUI/DynamicBitmaps/Heroes/Hero_H0016_Large"/>
    </Icons>
  </GuiElement>
  <GuiElement Name="Hero_H0011">
    <Title>%Hero_H0011_Title</Title>
    <Description>%Hero_H0011_Biography</Description>
    <Icons>
      <Icon Size="Small" Path="GUI/DynamicBitmaps/Heroes/Hero_H0011"/>
      <Icon Size="Large" Path="GUI/DynamicBitmaps/Heroes/Hero_H0011_Large"/>
    </Icons>
  </GuiElement>
  <GuiElement Name="Hero_H0017">
    <Title>%Hero_H0017_Title</Title>
    <Description>%Hero_H0017_Biography</Description>
    <Icons>
      <Icon Size="Small" Path="GUI/DynamicBitmaps/Heroes/Hero_H0017"/>
      <Icon Size="Large" Path="GUI/DynamicBitmaps/Heroes/Hero_H0017_Large"/>
    </Icons>
  </GuiElement>
  <GuiElement Name="Hero_H0018">
    <Title>%Hero_H0018_Title</Title>
    <Description>%Hero_H0018_Biography</Description>
    <Icons>
      <Icon Size="Small" Path="GUI/DynamicBitmaps/Heroes/Hero_H0018"/>
      <Icon Size="Large" Path="GUI/DynamicBitmaps/Heroes/Hero_H0018_Large"/>
    </Icons>
  </GuiElement>
  <GuiElement Name="Hero_H0019">
    <Title>%Hero_H0019_Title</Title>
    <Description>%Hero_H0019_Biography</Description>
    <Icons>
      <Icon Size="Small" Path="GUI/DynamicBitmaps/Heroes/Hero_H0019"/>
      <Icon Size="Large" Path="GUI/DynamicBitmaps/Heroes/Hero_H0019_Large"/>
    </Icons>
  </GuiElement>
  <GuiElement Name="Hero_H0020">
    <Title>%Hero_H0020_Title</Title>
    <Description>%Hero_H0020_Biography</Description>
    <Icons>
      <Icon Size="Small" Path="GUI/DynamicBitmaps/Heroes/Hero_H0020"/>
      <Icon Size="Large" Path="GUI/DynamicBitmaps/Heroes/Hero_H0020_Large"/>
    </Icons>
  </GuiElement>
  <GuiElement Name="Hero_H0021">
    <Title>%Hero_H0021_Title</Title>
    <Description>%Hero_H0021_Biography</Description>
    <Icons>
      <Icon Size="Small" Path="GUI/DynamicBitmaps/Heroes/Hero_H0021"/>
      <Icon Size="Large" Path="GUI/DynamicBitmaps/Heroes/Hero_H0021_Large"/>
    </Icons>
  </GuiElement>
  <GuiElement Name="Hero_H0022">
    <Title>%Hero_H0022_Title</Title>
    <Description>%Hero_H0022_Biography</Description>
    <Icons>
      <Icon Size="Small" Path="GUI/DynamicBitmaps/Heroes/Hero_H0022"/>
      <Icon Size="Large" Path="GUI/DynamicBitmaps/Heroes/Hero_H0022_Large"/>
    </Icons>
  </GuiElement>
  <GuiElement Name="Hero_H0023">
    <Title>%Hero_H0023_Title</Title>
    <Description>%Hero_H0023_Biography</Description>
    <Icons>
      <Icon Size="Small" Path="GUI/DynamicBitmaps/Heroes/Hero_H0023"/>
      <Icon Size="Large" Path="GUI/DynamicBitmaps/Heroes/Hero_H0023_Large"/>
    </Icons>
  </GuiElement>
  <GuiElement Name="Hero_H0024">
    <Title>%Hero_H0024_Title</Title>
    <Description>%Hero_H0024_Biography</Description>
    <Icons>
      <Icon Size="Small" Path="GUI/DynamicBitmaps/Heroes/Hero_H0024"/>
      <Icon Size="Large" Path="GUI/DynamicBitmaps/Heroes/Hero_H0024_Large"/>
    </Icons>
  </GuiElement>
  <GuiElement Name="Hero_H0025">
    <Title>%Hero_H0025_Title</Title>
    <Description>%Hero_H0025_Biography</Description>
    <Icons>
      <Icon Size="Small" Path="GUI/DynamicBitmaps/Heroes/Hero_H0025"/>
      <Icon Size="Large" Path="GUI/DynamicBitmaps/Heroes/Hero_H0025_Large"/>
    </Icons>
  </GuiElement>
  <GuiElement Name="Hero_H0026">
    <Title>%Hero_H0026_Title</Title>
    <Description>%Hero_H0026_Biography</Description>
    <Icons>
      <Icon Size="Small" Path="GUI/DynamicBitmaps/Heroes/Hero_H0026"/>
      <Icon Size="Large" Path="GUI/DynamicBitmaps/Heroes/Hero_H0026_Large"/>
    </Icons>
  </GuiElement>
  <GuiElement Name="Hero_H0027">
    <Title>%Hero_H0027_Title</Title>
    <Description>%Hero_H0027_Biography</Description>
    <Icons>
      <Icon Size="Small" Path="GUI/DynamicBitmaps/Heroes/Hero_H0027"/>
      <Icon Size="Large" Path="GUI/DynamicBitmaps/Heroes/Hero_H0027_Large"/>
    </Icons>
  </GuiElement>
  <GuiElement Name="Hero_H0028">
    <Title>%Hero_H0028_Title</Title>
    <Description>%Hero_H0028_Biography</Description>
    <Icons>
      <Icon Size="Small" Path="GUI/DynamicBitmaps/Heroes/Hero_H0028"/>
      <Icon Size="Large" Path="GUI/DynamicBitmaps/Heroes/Hero_H0028_Large"/>
    </Icons>
  </GuiElement>
</Datatable>
